setup.py
nicoerenkuk/test.py
nicoerenkuk.egg-info/PKG-INFO
nicoerenkuk.egg-info/SOURCES.txt
nicoerenkuk.egg-info/dependency_links.txt
nicoerenkuk.egg-info/top_level.txt